orbitit/Geom3D.py
orbitit/Geom4D.py
orbitit/Heptagons.py
orbitit/PS.py
orbitit/Scene_24Cell.py
orbitit/Scene_5Cell.py
orbitit/Scene_8Cell.py
orbitit/Scene_EqlHeptA5xI.py
orbitit/Scene_EqlHeptA5xI_GD.py
orbitit/Scene_EqlHeptA5xI_GI.py
orbitit/Scene_EqlHeptFromKite.py
orbitit/Scene_EqlHeptS4A4.py
orbitit/Scene_EqlHeptS4xI.py
orbitit/Scene_FldHeptA4.py
orbitit/Scene_FldHeptA5.py
orbitit/Scene_FldHeptS4.py
orbitit/Scene_Rectified24Cell.py
orbitit/Scene_Rectified8Cell.py
orbitit/Scenes3D.py
orbitit/X3D.py
orbitit/__init__.py
orbitit/__main__.py
orbitit/geom_gui.py
orbitit/geomtypes.py
orbitit/glue.py
orbitit/indent.py
orbitit/isometry.py
orbitit/orbit.py
orbitit/rgb.py
orbitit/scene_orbit.py
orbitit-0.5.4.dist-info/LICENSE.txt
orbitit-0.5.4.dist-info/METADATA
orbitit-0.5.4.dist-info/WHEEL
orbitit-0.5.4.dist-info/top_level.txt
orbitit-0.5.4.dist-info/RECORD
