Metadata-Version: 2.1
Name: orbitit
Version: 0.5.4
Summary: Utility for modelling polyhedra
Home-page: https://github.com/marcelteun/Orbitit
Author: marcelteun
Author-email: marcelteun@gmail.com
License: GNU Public License version 2
Download-URL: https://github.com/marcelteun/Orbitit/archive/refs/tags/0.4.0.zip
Keywords: orbitit,polyhedra,heptagons
Platform: UNKNOWN
Classifier: Operating System :: OS Independent
Classifier: License :: OSI Approved :: GNU General Public License v2 (GPLv2)
Classifier: Programming Language :: Python :: 3
Requires-Python: >=3.6
License-File: LICENSE.txt
Requires-Dist: python-config
Requires-Dist: wxPython (>=4.0.0)
Requires-Dist: pyopengl
